{
  "kind": "collectionType",
  "collectionName": "modules",
  "info": {
    "name": "module"
  },
  "options": {
    "increments": true,
    "timestamps": true
  },
  "attributes": {
    "course": {
      "via": "modules",
      "model": "course"
    },
    "order": {
      "type": "integer"
    },
    "name": {
      "type": "string",
      "required": true
    },
    "description": {
      "type": "richtext",
      "required": true
    },
    "link": {
      "type": "string",
      "required": true
    }
  }
}
